flask_tracing.py
Flask_Tracing-0.3.1.dist-info/LICENSE
Flask_Tracing-0.3.1.dist-info/METADATA
Flask_Tracing-0.3.1.dist-info/WHEEL
Flask_Tracing-0.3.1.dist-info/top_level.txt
Flask_Tracing-0.3.1.dist-info/RECORD
