Metadata-Version: 2.1
Name: Flask-Tracing
Version: 0.3.1
Summary: Tracing utilities for your flask application.
Home-page: https://github.com/Handsome2734/Flask-Tracing
Author: Handsome2734
Author-email: songbowen1229@gmail.com
License: BSD
Platform: any
Classifier: Environment :: Web Environment
Classifier: Intended Audience :: Developers
Classifier: License :: OSI Approved :: BSD License
Classifier: Operating System :: OS Independent
Classifier: Programming Language :: Python
Classifier: Topic :: Internet :: WWW/HTTP :: Dynamic Content
Classifier: Topic :: Software Development :: Libraries :: Python Modules
Requires-Dist: Flask
